neuron_tracing/__init__.py
neuron_tracing/cli/__init__.py
neuron_tracing/cli/tracing_cli_2D.py
neuron_tracing/cli/tracing_cli_3D.py
neuron_tracing/lib/__init__.py
neuron_tracing/lib/klib/TiffFile.py
neuron_tracing/lib/klib/__init__.py
neuron_tracing/lib/klib/baseio.py
neuron_tracing/lib/klib/image_history_buffer.py
neuron_tracing/lib/klib/simulator.py
neuron_tracing/lib/klib/glib/ConvPlotTools.py
neuron_tracing/lib/klib/glib/Converter.py
neuron_tracing/lib/klib/glib/Draw2DTools.py
neuron_tracing/lib/klib/glib/Draw3DStack.py
neuron_tracing/lib/klib/glib/Draw3DTools.py
neuron_tracing/lib/klib/glib/DrawSimulationSWC.py
neuron_tracing/lib/klib/glib/DrawSimulationSWCModel.py
neuron_tracing/lib/klib/glib/EvaluateModel.py
neuron_tracing/lib/klib/glib/GANParser.py
neuron_tracing/lib/klib/glib/GANRefinerParser.py
neuron_tracing/lib/klib/glib/ImageEvaluation.py
neuron_tracing/lib/klib/glib/ImageUtils.py
neuron_tracing/lib/klib/glib/Inputer.py
neuron_tracing/lib/klib/glib/Label.py
neuron_tracing/lib/klib/glib/LabelDefinition.py
neuron_tracing/lib/klib/glib/Mail.py
neuron_tracing/lib/klib/glib/Obj3D.py
neuron_tracing/lib/klib/glib/Parser.py
neuron_tracing/lib/klib/glib/PlotTools.py
neuron_tracing/lib/klib/glib/Reader.py
neuron_tracing/lib/klib/glib/SWCExtractor.py
neuron_tracing/lib/klib/glib/SamplingTools.py
neuron_tracing/lib/klib/glib/SlidingWindow.py
neuron_tracing/lib/klib/glib/TiffFile.py
neuron_tracing/lib/klib/glib/Transformation2D.py
neuron_tracing/lib/klib/glib/Transformation3D.py
neuron_tracing/lib/klib/glib/Transformations.py
neuron_tracing/lib/klib/glib/Utils.py
neuron_tracing/lib/klib/glib/Writer.py
neuron_tracing/lib/klib/glib/__init__.py
neuron_tracing/lib/klib/glib/docopt.py
neuron_tracing/lib/swclib/__init__.py
neuron_tracing/lib/swclib/euclidean_point.py
neuron_tracing/lib/swclib/exceptions.py
neuron_tracing/lib/swclib/swc_io.py
neuron_tracing/lib/swclib/swc_node.py
neuron_tracing/lib/swclib/swc_tree.py
neuron_tracing/model/__init__.py
neurontracing-1.0.4.dist-info/LICENSE.txt
neurontracing-1.0.4.dist-info/METADATA
neurontracing-1.0.4.dist-info/WHEEL
neurontracing-1.0.4.dist-info/entry_points.txt
neurontracing-1.0.4.dist-info/top_level.txt
neurontracing-1.0.4.dist-info/RECORD
