Metadata-Version: 2.1
Name: neurontracing
Version: 1.0.4
Summary: neuron_tracing first edition
Home-page: https://github.com/SupermeLC/Snake-for-Neuron-Tracing
Author: LiuChao
Author-email: supermeliu@zju.edu.cn
License: UNKNOWN
Platform: UNKNOWN
License-File: LICENSE.txt
Requires-Dist: numpy (==1.20.3)
Requires-Dist: anytree (>=2.7.2)
Requires-Dist: kdtree (>=0.16)
Requires-Dist: rtree (>=0.8)
Requires-Dist: jsonschema (>=3.2.0)
Requires-Dist: pandas (>=1.3.2)
Requires-Dist: matplotlib (>=3.0.0)
Requires-Dist: scikit-image (==0.18.3)
Requires-Dist: scipy (==1.7.3)
Requires-Dist: Pillow (>=8.4.0)
Requires-Dist: opencv-python (>=4.5.5.64)
